stream_manager/__init__.py
stream_manager/exceptions.py
stream_manager/streammanagerclient.py
stream_manager/util.py
stream_manager/utilinternal.py
stream_manager/data/__init__.py
stream_manager-1.1.1.dist-info/LICENSE
stream_manager-1.1.1.dist-info/METADATA
stream_manager-1.1.1.dist-info/NOTICE
stream_manager-1.1.1.dist-info/WHEEL
stream_manager-1.1.1.dist-info/top_level.txt
stream_manager-1.1.1.dist-info/RECORD
