Metadata-Version: 2.1
Name: stream-manager
Version: 1.1.1
Summary: The AWS IoT Greengrass Stream Manager SDK for Python
Home-page: UNKNOWN
Author: Amazon Web Services
License: Apache License 2.0
Platform: UNKNOWN
Classifier: Development Status :: 5 - Production/Stable
Classifier: Intended Audience :: Developers
Classifier: Natural Language :: English
Classifier: License :: OSI Approved :: Apache Software License
Classifier: Programming Language :: Python
Classifier: Programming Language :: Python :: 3.7
Classifier: Programming Language :: Python :: 3.8
Classifier: Programming Language :: Python :: 3.9
Classifier: Programming Language :: Python :: 3.10
License-File: LICENSE
License-File: NOTICE
Requires-Dist: cbor2 (~=5.4.2)
